[
  {
    "name": "hhnrakt",
    "dataset": "bfvp",
    "label": "Current Wave Number (=BFHHNR)",
    "categories": {
      "values": [],
      "labels": []
    },
    "scale": "number",
    "label_de": "Aktuelle Haushaltsnummer (=BFHHNR)",
    "study": "soep-core",
    "statistics": {
      "Min.": 3301.0,
      "1st Qu.": 291869.75,
      "Median": 2016373.0,
      "Mean": 1639173.5837004406,
      "3rd Qu.": 3064887.75,
      "Max.": 3342904.0,
      "valid": 454,
      "invalid": 0
    }
  },
  {
    "name": "hhnr",
    "dataset": "bfvp",
    "label": "Original Household Number",
    "categories": {
      "values": [],
      "labels": []
    },
    "scale": "number",
    "label_de": "Ursprungshaushaltsnummer",
    "study": "soep-core",
    "statistics": {
      "Min.": 3301.0,
      "1st Qu.": 294935.75,
      "Median": 2016373.0,
      "Mean": 1637421.0462555066,
      "3rd Qu.": 3064887.75,
      "Max.": 3342904.0,
      "valid": 454,
      "invalid": 0
    }
  },
  {
    "name": "persnr",
    "dataset": "bfvp",
    "label": "Unchanging ID Person Surveyed",
    "categories": {
      "values": [],
      "labels": []
    },
    "scale": "number",
    "label_de": "Unveraenderliche Personennr. Befragungsperson",
    "study": "soep-core",
    "statistics": {
      "Min.": 33002.0,
      "1st Qu.": 2939376.5,
      "Median": 20163701.5,
      "Mean": 16394862.235682819,
      "3rd Qu.": 30648801.75,
      "Max.": 33429002.0,
      "valid": 454,
      "invalid": 0
    }
  },
  {
    "name": "syear",
    "dataset": "bfvp",
    "label": "Survey Year",
    "categories": {
      "values": [],
      "labels": []
    },
    "scale": "number",
    "label_de": "Befragungsjahr",
    "study": "soep-core",
    "statistics": {
      "Min.": 2015.0,
      "1st Qu.": 2015.0,
      "Median": 2015.0,
      "Mean": 2015.0,
      "3rd Qu.": 2015.0,
      "Max.": 2015.0,
      "valid": 454,
      "invalid": 0
    }
  },
  {
    "name": "cid",
    "dataset": "bfvp",
    "label": "Original Household Number",
    "categories": {
      "values": [],
      "labels": []
    },
    "scale": "number",
    "label_de": "Ursprungshaushaltsnummer",
    "study": "soep-core",
    "statistics": {
      "Min.": 3301.0,
      "1st Qu.": 294935.75,
      "Median": 2016373.0,
      "Mean": 1637421.0462555066,
      "3rd Qu.": 3064887.75,
      "Max.": 3342904.0,
      "valid": 454,
      "invalid": 0
    }
  },
  {
    "name": "bfhhnr",
    "dataset": "bfvp",
    "label": "Current Wave HH Number (=HHNRAKT)",
    "categories": {
      "values": [],
      "labels": []
    },
    "scale": "number",
    "label_de": "Aktuelle Haushaltsnummer (HHNRAKT)",
    "study": "soep-core",
    "statistics": {
      "Min.": 3301.0,
      "1st Qu.": 291869.75,
      "Median": 2016373.0,
      "Mean": 1639173.5837004406,
      "3rd Qu.": 3064887.75,
      "Max.": 3342904.0,
      "valid": 454,
      "invalid": 0
    }
  },
  {
    "name": "hid",
    "dataset": "bfvp",
    "label": "Current Wave Number (=BFHHNR)",
    "categories": {
      "values": [],
      "labels": []
    },
    "scale": "number",
    "label_de": "Aktuelle Haushaltsnummer (=BFHHNR)",
    "study": "soep-core",
    "statistics": {
      "Min.": 3301.0,
      "1st Qu.": 291869.75,
      "Median": 2016373.0,
      "Mean": 1639173.5837004406,
      "3rd Qu.": 3064887.75,
      "Max.": 3342904.0,
      "valid": 454,
      "invalid": 0
    }
  },
  {
    "name": "pid",
    "dataset": "bfvp",
    "label": "Unchanging ID Person Surveyed",
    "categories": {
      "values": [],
      "labels": []
    },
    "scale": "number",
    "label_de": "Unveraenderliche Personennr. Befragungsperson",
    "study": "soep-core",
    "statistics": {
      "Min.": 33002.0,
      "1st Qu.": 2939376.5,
      "Median": 20163701.5,
      "Mean": 16394862.235682819,
      "3rd Qu.": 30648801.75,
      "Max.": 33429002.0,
      "valid": 454,
      "invalid": 0
    }
  },
  {
    "name": "vpersnr",
    "dataset": "bfvp",
    "label": "ID person surveyed",
    "categories": {
      "values": [],
      "labels": []
    },
    "scale": "number",
    "label_de": "Personennummer der verstorbenen Person",
    "study": "soep-core",
    "statistics": {
      "Min.": 33001.0,
      "1st Qu.": 2900574.75,
      "Median": 20163799.0,
      "Mean": 16376261.682819383,
      "3rd Qu.": 30648875.5,
      "Max.": 33429099.0,
      "valid": 454,
      "invalid": 0
    }
  },
  {
    "name": "vpnr",
    "dataset": "bfvp",
    "label": "Consecutive Nummer Person Surveyed (gen)",
    "categories": {
      "values": [],
      "labels": []
    },
    "scale": "number",
    "label_de": "Laufende Nummer(gen.) zu Befragungspersonen",
    "study": "soep-core",
    "statistics": {
      "Min.": 0.0,
      "1st Qu.": 0.0,
      "Median": 0.0,
      "Mean": 0.0,
      "3rd Qu.": 0.0,
      "Max.": 0.0,
      "valid": 454,
      "invalid": 0
    }
  },
  {
    "name": "welle",
    "dataset": "bfvp",
    "label": "Survey Year",
    "categories": {
      "values": [],
      "labels": []
    },
    "scale": "number",
    "label_de": "Erhebungsjahr",
    "study": "soep-core",
    "statistics": {
      "Min.": 2015.0,
      "1st Qu.": 2015.0,
      "Median": 2015.0,
      "Mean": 2015.0,
      "3rd Qu.": 2015.0,
      "Max.": 2015.0,
      "valid": 454,
      "invalid": 0
    }
  },
  {
    "name": "sample1",
    "dataset": "bfvp",
    "label": "Subsample Identifier",
    "categories": {
      "values": [
        -6,
        -5,
        -4,
        -3,
        -2,
        -1,
        1,
        2,
        3,
        4,
        5,
        6,
        7,
        8,
        9,
        10,
        11,
        12,
        13,
        14,
        15,
        16,
        19,
        20,
        21,
        22,
        23,
        24,
        29,
        30,
        31,
        60,
        61,
        62,
        63,
        64,
        65,
        66
      ],
      "labels": [
        "[-6] Version of questionnaire with modified filtering",
        "[-5] Not included in this version of the questionnaire",
        "[-4] Inadmissible multiple response",
        "[-3] Answer improbable",
        "[-2] Does not apply",
        "[-1] No Answer",
        "[1] A German HH Head, West, 1984",
        "[2] B1 Turkish HH Head, 1984",
        "[3] B2 Yugoslav HH Head, 1984",
        "[4] B3 Greek HH Head, 1984",
        "[5] B4 Italian HH Head, 1984",
        "[6] B5 Spanish HH Head, 1984",
        "[7] C German HH Head, East, 1990",
        "[8] D1 Immigrant W. Germany (1984-1994), 1994/95",
        "[9] D2 Immigrant W. Germany (1984-1994), 1994/95",
        "[10] E1 Refreshment (PAPI), 1998",
        "[11] E2 Refreshment (CAPI), 1998",
        "[12] F1 Refreshment, 2000",
        "[13] F2 Refreshment, Additional Foreigner Addresses, 2000",
        "[14] G1 High Income (PreTest), 2002",
        "[15] G2 High Income, 2002",
        "[16] H Refreshment, 2006",
        "[19] I Refreshment, Incentivation, 2009",
        "[20] J Refreshment, 2011",
        "[21] K Refreshment, 2012",
        "[22] I2 Refreshment IS, 2012",
        "[23] Special Survey (Laboratory Sample), 2012",
        "[24] M1 Migration (1995-2011), 2013",
        "[29] M2 Migration (2009-2013), 2015",
        "[30] M3 Refugees (01/2013-01/2016), 2016",
        "[31] M4 Refugee Families (01/2013-01/2016), 2016",
        "[60] L2/3 FiD Screening, Low Income, 2010/11",
        "[61] L2/3 FiD Screening, Single Parent, 2010/11",
        "[62] L2/3 FiD Screening, Families with Several Children, 2010/11",
        "[63] L1 FiD Birth Cohort 2007, 2010/11",
        "[64] L1 FiD Birth Cohort 2008, 2010/11",
        "[65] L1 FiD Birth Cohort 2009, 2010/11",
        "[66] L1 FiD Birth Cohort 2010, 2010/11"
      ],
      "labels_de": [
        "[-6] Fragebogenversion mit geaenderter Filterfuehrung",
        "[-5] In Fragebogenversion nicht enthalten",
        "[-4] Unzulaessige Mehrfachantwort",
        "[-3] nicht valide",
        "[-2] trifft nicht zu",
        "[-1] keine Angabe",
        "[1] A Deutscher HV (West)",
        "[2] B1 Tuerkischer HV",
        "[3] B2 Jugoslawischer HV",
        "[4] B3 Griechischer HV",
        "[5] B4 Italienischer HV",
        "[6] B5 Spanischer HV",
        "[7] C Deutscher HV (Ost)",
        "[8] D1 Zuwanderung nach Westdeutschland",
        "[9] D2 Zuwanderung nach Westdeutschland",
        "[10] E1 (PAPI)",
        "[11] E2 (CAPI)",
        "[12] F1 ISOEP (Innovation)",
        "[13] F2 ISOEP, Zusatzbegehung Auslaenderadr.",
        "[14] G1 Hocheinkommensbezieher (PreTest)",
        "[15] G2 Hocheinkommensbezieher",
        "[16] H Ergaenzung 2006",
        "[19] I Incentivierung 2009",
        "[20] J Aufstockung 2011",
        "[21] K Aufstockung 2012",
        "[22] I2 Aufstockung IS 2012",
        "[23] Sondererhebung 2012 (Laborstichprobe)",
        "[24] M1 2013 Migration (1995-2010)",
        "[29] M2 2015 Migration (2009-2013)",
        "[30] M3 2016 Flucht (2013-2015)",
        "[31] M4 2016 Flucht/Familien (2013-2015)",
        "[60] L2/3 FiD Screening 2010/11 Niedrigeinkommen",
        "[61] L2/3 FiD Screening 2010/11 Alleinerziehende",
        "[62] L2/3 FiD Screening 2010/11 Mehrkindfamilien",
        "[63] L1 FiD Geburtskohorte 2007",
        "[64] L1 FiD Geburtskohorte 2008",
        "[65] L1 FiD Geburtskohorte 2009",
        "[66] L1 FiD Geburtskohorte 2010"
      ],
      "frequencies": [
        0,
        0,
        0,
        0,
        0,
        0,
        53,
        4,
        3,
        0,
        3,
        1,
        33,
        2,
        0,
        0,
        0,
        64,
        3,
        0,
        16,
        20,
        0,
        80,
        36,
        0,
        0,
        41,
        0,
        0,
        0,
        25,
        12,
        32,
        4,
        9,
        2,
        11
      ]
    },
    "scale": "cat",
    "label_de": "Stichprobenkennzeichen",
    "study": "soep-core",
    "statistics": {
      "valid": 454,
      "invalid": 0
    }
  },
  {
    "name": "bfpnr",
    "dataset": "bfvp",
    "label": "Serial Number Person Died (gen)",
    "categories": {
      "values": [
        -6,
        -5,
        -4,
        -3,
        -2,
        -1,
        98,
        99,
        1,
        2,
        3,
        4,
        6,
        5
      ],
      "labels": [
        "[-6] Version of questionnaire with modified filtering",
        "[-5] Not included in this version of the questionnaire",
        "[-4] Inadmissible multiple response",
        "[-3] Answer improbable",
        "[-2] Does not apply",
        "[-1] No Answer",
        "[98] Former Core Sample Member",
        "[99] Not Core Sample Member",
        "1",
        "2",
        "3",
        "4",
        "6",
        "5"
      ],
      "labels_de": [
        "[-6] Fragebogenversion mit geaenderter Filterfuehrung",
        "[-5] In Fragebogenversion nicht enthalten",
        "[-4] Unzulaessige Mehrfachantwort",
        "[-3] nicht valide",
        "[-2] trifft nicht zu",
        "[-1] keine Angabe",
        "[98] Frueheres Stichprobenmitglied",
        "[99] Kein Stichprobenmitglied"
      ],
      "missings": [
        false,
        true,
        true,
        true,
        true,
        true
      ],
      "frequencies": [
        0,
        0,
        0,
        0,
        0,
        0,
        0,
        7,
        243,
        177,
        16,
        7,
        3,
        1
      ]
    },
    "scale": "cat",
    "label_de": "Laufende Nummer der Auskunftsperson",
    "study": "soep-core",
    "statistics": {
      "valid": 454,
      "invalid": 0
    }
  },
  {
    "name": "bfvp0101",
    "dataset": "bfvp",
    "label": "sex person died",
    "categories": {
      "values": [
        -6,
        -5,
        -4,
        -3,
        -2,
        -1,
        1,
        2
      ],
      "labels": [
        "[-6] Version of questionnaire with modified filtering",
        "[-5] Not included in this version of the questionnaire",
        "[-4] Inadmissible multiple response",
        "[-3] Answer improbable",
        "[-2] Does not apply",
        "[-1] No Answer",
        "[1] Male",
        "[2] Female"
      ],
      "labels_de": [
        "[-6] Fragebogenversion mit geaenderter Filterfuehrung",
        "[-5] In Fragebogenversion nicht enthalten",
        "[-4] Unzulaessige Mehrfachantwort",
        "[-3] nicht valide",
        "[-2] trifft nicht zu",
        "[-1] keine Angabe",
        "[1] Maennlich",
        "[2] Weiblich"
      ],
      "frequencies": [
        0,
        0,
        0,
        0,
        0,
        0,
        245,
        209
      ]
    },
    "scale": "cat",
    "label_de": "Geschlecht der verstorbenen Person",
    "study": "soep-core",
    "statistics": {
      "valid": 454,
      "invalid": 0
    }
  },
  {
    "name": "bfvp0102",
    "dataset": "bfvp",
    "label": "year of birth person died",
    "categories": {
      "values": [],
      "labels": []
    },
    "scale": "number",
    "label_de": "Geburtsjahr der verstorbenen Person",
    "study": "soep-core",
    "statistics": {
      "Min.": 1913.0,
      "1st Qu.": 1928.0,
      "Median": 1936.0,
      "Mean": 1938.2070484581498,
      "3rd Qu.": 1945.0,
      "Max.": 1999.0,
      "valid": 454,
      "invalid": 0
    }
  },
  {
    "name": "bfvp02",
    "dataset": "bfvp",
    "label": "kinship relationship to deceased",
    "categories": {
      "values": [
        -6,
        -5,
        -4,
        -3,
        -2,
        -1,
        1,
        2,
        3,
        4
      ],
      "labels": [
        "[-6] Version of questionnaire with modified filtering",
        "[-5] Not included in this version of the questionnaire",
        "[-4] Inadmissible multiple response",
        "[-3] Answer improbable",
        "[-2] Does not apply",
        "[-1] No Answer",
        "[1] my mother/my father",
        "[2] my husband/wife/partner",
        "[3] my daughter/my son",
        "[4] other person"
      ],
      "labels_de": [
        "[-6] Fragebogenversion mit geaenderter Filterfuehrung",
        "[-5] In Fragebogenversion nicht enthalten",
        "[-4] Unzulaessige Mehrfachantwort",
        "[-3] nicht valide",
        "[-2] trifft nicht zu",
        "[-1] keine Angabe",
        "[1] meine Mutter/ mein Vater",
        "[2] mein Ehe-/Lebenspartner",
        "[3] meine Tochter/mein Sohn",
        "[4] andere Person"
      ],
      "frequencies": [
        0,
        0,
        0,
        0,
        0,
        1,
        305,
        97,
        13,
        38
      ]
    },
    "scale": "cat",
    "label_de": "Verwandtschaftsverhaeltnis zur verstorb. Pers.",
    "study": "soep-core",
    "statistics": {
      "valid": 453,
      "invalid": 1
    }
  },
  {
    "name": "bfvp03",
    "dataset": "bfvp",
    "label": "age of person died",
    "categories": {
      "values": [],
      "labels": []
    },
    "scale": "number",
    "label_de": "Alter der verstorbenen Person",
    "study": "soep-core",
    "statistics": {
      "Min.": 14.0,
      "1st Qu.": 69.0,
      "Median": 78.0,
      "Mean": 75.50892857142857,
      "3rd Qu.": 85.0,
      "Max.": 102.0,
      "valid": 448,
      "invalid": 6
    }
  },
  {
    "name": "bfvp04",
    "dataset": "bfvp",
    "label": "person died lived in local hh?",
    "categories": {
      "values": [
        -6,
        -5,
        -4,
        -3,
        -2,
        -1,
        1,
        2
      ],
      "labels": [
        "[-6] Version of questionnaire with modified filtering",
        "[-5] Not included in this version of the questionnaire",
        "[-4] Inadmissible multiple response",
        "[-3] Answer improbable",
        "[-2] Does not apply",
        "[-1] No Answer",
        "[1] Yes",
        "[2] No"
      ],
      "labels_de": [
        "[-6] Fragebogenversion mit geaenderter Filterfuehrung",
        "[-5] In Fragebogenversion nicht enthalten",
        "[-4] Unzulaessige Mehrfachantwort",
        "[-3] nicht valide",
        "[-2] trifft nicht zu",
        "[-1] keine Angabe",
        "[1] Ja",
        "[2] Nein"
      ],
      "frequencies": [
        0,
        0,
        0,
        0,
        0,
        0,
        123,
        331
      ]
    },
    "scale": "cat",
    "label_de": "Lebte Verstorbene/r im hiesigen HH",
    "study": "soep-core",
    "statistics": {
      "valid": 454,
      "invalid": 0
    }
  },
  {
    "name": "bfvp05",
    "dataset": "bfvp",
    "label": "person died was SOEP attendant",
    "categories": {
      "values": [
        -6,
        -5,
        -4,
        -3,
        -2,
        -1,
        1,
        2,
        3
      ],
      "labels": [
        "[-6] Version of questionnaire with modified filtering",
        "[-5] Not included in this version of the questionnaire",
        "[-4] Inadmissible multiple response",
        "[-3] Answer improbable",
        "[-2] Does not apply",
        "[-1] No Answer",
        "[1] yes, did participate",
        "[2] no, did not participate",
        "[3] Do Not Know"
      ],
      "labels_de": [
        "[-6] Fragebogenversion mit geaenderter Filterfuehrung",
        "[-5] In Fragebogenversion nicht enthalten",
        "[-4] Unzulaessige Mehrfachantwort",
        "[-3] nicht valide",
        "[-2] trifft nicht zu",
        "[-1] keine Angabe",
        "[1] Ja, hat teilgenommen",
        "[2] Nein, hat nicht teilgenommen",
        "[3] Weiss nicht"
      ],
      "frequencies": [
        0,
        0,
        0,
        0,
        123,
        0,
        28,
        296,
        7
      ]
    },
    "scale": "cat",
    "label_de": "Verstorbene/r Teilnehmer am SOEP",
    "study": "soep-core",
    "statistics": {
      "valid": 331,
      "invalid": 123
    }
  },
  {
    "name": "bfvp06",
    "dataset": "bfvp",
    "label": "domestic environment of deceased in last year alive",
    "categories": {
      "values": [
        -6,
        -5,
        -4,
        -3,
        -2,
        -1,
        1,
        2,
        3,
        4,
        5,
        6,
        7
      ],
      "labels": [
        "[-6] Version of questionnaire with modified filtering",
        "[-5] Not included in this version of the questionnaire",
        "[-4] Inadmissible multiple response",
        "[-3] Answer improbable",
        "[-2] Does not apply",
        "[-1] No Answer",
        "[1] alone in own household",
        "[2] together with partner in own household",
        "[3] together with other relative in privat household",
        "[4] in senior-friendly residence",
        "[5] in home for the elderly",
        "[6] in hospital",
        "[7] other environment"
      ],
      "labels_de": [
        "[-6] Fragebogenversion mit geaenderter Filterfuehrung",
        "[-5] In Fragebogenversion nicht enthalten",
        "[-4] Unzulaessige Mehrfachantwort",
        "[-3] nicht valide",
        "[-2] trifft nicht zu",
        "[-1] keine Angabe",
        "[1] Allein im eigenen Haushalt",
        "[2] Zusammen mit (Ehe-)Partner im eigenen HH",
        "[3] Zusammen mit Sonst.aus Fam. in Privat-HH",
        "[4] In seniorengerechten Wohnanlage",
        "[5] In ALten-,Pflegeheim",
        "[6] In Klinik, Krankenhaus",
        "[7] Sonstiges Umfeld"
      ],
      "frequencies": [
        0,
        0,
        0,
        0,
        123,
        0,
        108,
        130,
        25,
        6,
        53,
        6,
        3
      ]
    },
    "scale": "cat",
    "label_de": "Haeusl.Umfeld Verstorb.letztes Lebensjahr",
    "study": "soep-core",
    "statistics": {
      "valid": 331,
      "invalid": 123
    }
  },
  {
    "name": "bfvp07",
    "dataset": "bfvp",
    "label": "focus of deceased person's life",
    "categories": {
      "values": [
        -6,
        -5,
        -4,
        -3,
        -2,
        -1,
        1,
        2,
        3,
        4,
        5
      ],
      "labels": [
        "[-6] Version of questionnaire with modified filtering",
        "[-5] Not included in this version of the questionnaire",
        "[-4] Inadmissible multiple response",
        "[-3] Answer improbable",
        "[-2] Does not apply",
        "[-1] No Answer",
        "[1] here in the house",
        "[2] In The Neighborhood",
        "[3] at close range, 1 h per feet",
        "[4] Lives Further Away In Germany",
        "[5] In A Foreign Country"
      ],
      "labels_de": [
        "[-6] Fragebogenversion mit geaenderter Filterfuehrung",
        "[-5] In Fragebogenversion nicht enthalten",
        "[-4] Unzulaessige Mehrfachantwort",
        "[-3] nicht valide",
        "[-2] trifft nicht zu",
        "[-1] keine Angabe",
        "[1] Hier im Haus",
        "[2] In der Nachbarschaft",
        "[3] In naeherer Entferng.,1 Std. zu Fuss",
        "[4] Weiter entfernt in D",
        "[5] Im Ausland"
      ],
      "frequencies": [
        0,
        0,
        0,
        0,
        123,
        2,
        26,
        36,
        114,
        120,
        33
      ]
    },
    "scale": "cat",
    "label_de": "Lebensmittelpunkt der/des Verstorbenen",
    "study": "soep-core",
    "statistics": {
      "valid": 329,
      "invalid": 125
    }
  },
  {
    "name": "bfvp08",
    "dataset": "bfvp",
    "label": "personal contact to deceased in last year",
    "categories": {
      "values": [
        -6,
        -5,
        -4,
        -3,
        -2,
        -1,
        1,
        2,
        3,
        4,
        5
      ],
      "labels": [
        "[-6] Version of questionnaire with modified filtering",
        "[-5] Not included in this version of the questionnaire",
        "[-4] Inadmissible multiple response",
        "[-3] Answer improbable",
        "[-2] Does not apply",
        "[-1] No Answer",
        "[1] daily, almost daily",
        "[2] at least once per week",
        "[3] at least once per month",
        "[4] Less Frequently",
        "[5] Not at All"
      ],
      "labels_de": [
        "[-6] Fragebogenversion mit geaenderter Filterfuehrung",
        "[-5] In Fragebogenversion nicht enthalten",
        "[-4] Unzulaessige Mehrfachantwort",
        "[-3] nicht valide",
        "[-2] trifft nicht zu",
        "[-1] keine Angabe",
        "[1] Taeglich, fast taeglich",
        "[2] Mind. 1x in der Woche",
        "[3] Mind. 1x im Monat",
        "[4] Seltener",
        "[5] Gar nicht"
      ],
      "frequencies": [
        0,
        0,
        0,
        0,
        123,
        0,
        138,
        114,
        42,
        26,
        11
      ]
    },
    "scale": "cat",
    "label_de": "Persoenl.Kontakt zu Verstorb.in letzten Jahr",
    "study": "soep-core",
    "statistics": {
      "valid": 331,
      "invalid": 123
    }
  },
  {
    "name": "bfvp09",
    "dataset": "bfvp",
    "label": "place of death",
    "categories": {
      "values": [
        -6,
        -5,
        -4,
        -3,
        -2,
        -1,
        1,
        2,
        3,
        4,
        5,
        6,
        7
      ],
      "labels": [
        "[-6] Version of questionnaire with modified filtering",
        "[-5] Not included in this version of the questionnaire",
        "[-4] Inadmissible multiple response",
        "[-3] Answer improbable",
        "[-2] Does not apply",
        "[-1] No Answer",
        "[1] at home",
        "[2] other, not own private household",
        "[3] in hospital",
        "[4] in home for the elderly",
        "[5] in hospice",
        "[6] at another place",
        "[7] Do Not Know"
      ],
      "labels_de": [
        "[-6] Fragebogenversion mit geaenderter Filterfuehrung",
        "[-5] In Fragebogenversion nicht enthalten",
        "[-4] Unzulaessige Mehrfachantwort",
        "[-3] nicht valide",
        "[-2] trifft nicht zu",
        "[-1] keine Angabe",
        "[1] Zu Hause",
        "[2] Anderer, nicht eigener Privat-HH",
        "[3] Im Krankenhaus",
        "[4] Im Alten-,Pflegeheim",
        "[5] Im Hospiz",
        "[6] An einem anderen Ort",
        "[7] Weiss nicht"
      ],
      "frequencies": [
        0,
        0,
        0,
        0,
        0,
        0,
        145,
        3,
        210,
        73,
        10,
        11,
        2
      ]
    },
    "scale": "cat",
    "label_de": "Sterbeort",
    "study": "soep-core",
    "statistics": {
      "valid": 454,
      "invalid": 0
    }
  },
  {
    "name": "bfvp1001",
    "dataset": "bfvp",
    "label": "cause of death: heart attack",
    "categories": {
      "values": [
        -6,
        -5,
        -4,
        -3,
        -2,
        -1,
        1
      ],
      "labels": [
        "[-6] Version of questionnaire with modified filtering",
        "[-5] Not included in this version of the questionnaire",
        "[-4] Inadmissible multiple response",
        "[-3] Answer improbable",
        "[-2] Does not apply",
        "[-1] No Answer",
        "[1] heart attack"
      ],
      "labels_de": [
        "[-6] Fragebogenversion mit geaenderter Filterfuehrung",
        "[-5] In Fragebogenversion nicht enthalten",
        "[-4] Unzulaessige Mehrfachantwort",
        "[-3] nicht valide",
        "[-2] trifft nicht zu",
        "[-1] keine Angabe",
        "[1] Herzinfarkt"
      ],
      "frequencies": [
        0,
        0,
        0,
        0,
        398,
        0,
        56
      ]
    },
    "scale": "cat",
    "label_de": "Todesursache Herzinfarkt",
    "study": "soep-core",
    "statistics": {
      "valid": 56,
      "invalid": 398
    }
  },
  {
    "name": "bfvp1002",
    "dataset": "bfvp",
    "label": "cause of death: cardiovascular disease",
    "categories": {
      "values": [
        -6,
        -5,
        -4,
        -3,
        -2,
        -1,
        1
      ],
      "labels": [
        "[-6] Version of questionnaire with modified filtering",
        "[-5] Not included in this version of the questionnaire",
        "[-4] Inadmissible multiple response",
        "[-3] Answer improbable",
        "[-2] Does not apply",
        "[-1] No Answer",
        "[1] cardiovascular disease"
      ],
      "labels_de": [
        "[-6] Fragebogenversion mit geaenderter Filterfuehrung",
        "[-5] In Fragebogenversion nicht enthalten",
        "[-4] Unzulaessige Mehrfachantwort",
        "[-3] nicht valide",
        "[-2] trifft nicht zu",
        "[-1] keine Angabe",
        "[1] Herz-Kreislauf-Erkrankung"
      ],
      "frequencies": [
        0,
        0,
        0,
        0,
        380,
        0,
        74
      ]
    },
    "scale": "cat",
    "label_de": "Todesursache Herz-Kreislauf-Erkrankung",
    "study": "soep-core",
    "statistics": {
      "valid": 74,
      "invalid": 380
    }
  },
  {
    "name": "bfvp1003",
    "dataset": "bfvp",
    "label": "cause of death: cancer",
    "categories": {
      "values": [
        -6,
        -5,
        -4,
        -3,
        -2,
        -1,
        1
      ],
      "labels": [
        "[-6] Version of questionnaire with modified filtering",
        "[-5] Not included in this version of the questionnaire",
        "[-4] Inadmissible multiple response",
        "[-3] Answer improbable",
        "[-2] Does not apply",
        "[-1] No Answer",
        "[1] cancer"
      ],
      "labels_de": [
        "[-6] Fragebogenversion mit geaenderter Filterfuehrung",
        "[-5] In Fragebogenversion nicht enthalten",
        "[-4] Unzulaessige Mehrfachantwort",
        "[-3] nicht valide",
        "[-2] trifft nicht zu",
        "[-1] keine Angabe",
        "[1] Krebserkrankung"
      ],
      "frequencies": [
        0,
        0,
        0,
        0,
        336,
        0,
        118
      ]
    },
    "scale": "cat",
    "label_de": "Todesursache Krebserkrankung",
    "study": "soep-core",
    "statistics": {
      "valid": 118,
      "invalid": 336
    }
  },
  {
    "name": "bfvp1004",
    "dataset": "bfvp",
    "label": "cause of death: epileptic stroke",
    "categories": {
      "values": [
        -6,
        -5,
        -4,
        -3,
        -2,
        -1,
        1
      ],
      "labels": [
        "[-6] Version of questionnaire with modified filtering",
        "[-5] Not included in this version of the questionnaire",
        "[-4] Inadmissible multiple response",
        "[-3] Answer improbable",
        "[-2] Does not apply",
        "[-1] No Answer",
        "[1] epileptic stroke"
      ],
      "labels_de": [
        "[-6] Fragebogenversion mit geaenderter Filterfuehrung",
        "[-5] In Fragebogenversion nicht enthalten",
        "[-4] Unzulaessige Mehrfachantwort",
        "[-3] nicht valide",
        "[-2] trifft nicht zu",
        "[-1] keine Angabe",
        "[1] Schlaganfall"
      ],
      "frequencies": [
        0,
        0,
        0,
        0,
        411,
        0,
        43
      ]
    },
    "scale": "cat",
    "label_de": "Todesursache Schlaganfall",
    "study": "soep-core",
    "statistics": {
      "valid": 43,
      "invalid": 411
    }
  },
  {
    "name": "bfvp1005",
    "dataset": "bfvp",
    "label": "cause of death: sever infectious disease",
    "categories": {
      "values": [
        -6,
        -5,
        -4,
        -3,
        -2,
        -1,
        1
      ],
      "labels": [
        "[-6] Version of questionnaire with modified filtering",
        "[-5] Not included in this version of the questionnaire",
        "[-4] Inadmissible multiple response",
        "[-3] Answer improbable",
        "[-2] Does not apply",
        "[-1] No Answer",
        "[1] severe infectious disease"
      ],
      "labels_de": [
        "[-6] Fragebogenversion mit geaenderter Filterfuehrung",
        "[-5] In Fragebogenversion nicht enthalten",
        "[-4] Unzulaessige Mehrfachantwort",
        "[-3] nicht valide",
        "[-2] trifft nicht zu",
        "[-1] keine Angabe",
        "[1] Schwere Infektionskrankheit"
      ],
      "frequencies": [
        0,
        0,
        0,
        0,
        419,
        0,
        35
      ]
    },
    "scale": "cat",
    "label_de": "Todesursache schwere Infektionskrankheit",
    "study": "soep-core",
    "statistics": {
      "valid": 35,
      "invalid": 419
    }
  },
  {
    "name": "bfvp1006",
    "dataset": "bfvp",
    "label": "cause of death: gastrointestinal tract disease",
    "categories": {
      "values": [
        -6,
        -5,
        -4,
        -3,
        -2,
        -1,
        1
      ],
      "labels": [
        "[-6] Version of questionnaire with modified filtering",
        "[-5] Not included in this version of the questionnaire",
        "[-4] Inadmissible multiple response",
        "[-3] Answer improbable",
        "[-2] Does not apply",
        "[-1] No Answer",
        "[1] gastrointestinal tract disease"
      ],
      "labels_de": [
        "[-6] Fragebogenversion mit geaenderter Filterfuehrung",
        "[-5] In Fragebogenversion nicht enthalten",
        "[-4] Unzulaessige Mehrfachantwort",
        "[-3] nicht valide",
        "[-2] trifft nicht zu",
        "[-1] keine Angabe",
        "[1] Krankheit Magen-Darm-Trakt"
      ],
      "frequencies": [
        0,
        0,
        0,
        0,
        445,
        0,
        9
      ]
    },
    "scale": "cat",
    "label_de": "Todesursache Magen-Darm-Trakt-Erkrankung",
    "study": "soep-core",
    "statistics": {
      "valid": 9,
      "invalid": 445
    }
  },
  {
    "name": "bfvp1007",
    "dataset": "bfvp",
    "label": "cause of death: respiratory disease",
    "categories": {
      "values": [
        -6,
        -5,
        -4,
        -3,
        -2,
        -1,
        1
      ],
      "labels": [
        "[-6] Version of questionnaire with modified filtering",
        "[-5] Not included in this version of the questionnaire",
        "[-4] Inadmissible multiple response",
        "[-3] Answer improbable",
        "[-2] Does not apply",
        "[-1] No Answer",
        "[1] respiratory disease"
      ],
      "labels_de": [
        "[-6] Fragebogenversion mit geaenderter Filterfuehrung",
        "[-5] In Fragebogenversion nicht enthalten",
        "[-4] Unzulaessige Mehrfachantwort",
        "[-3] nicht valide",
        "[-2] trifft nicht zu",
        "[-1] keine Angabe",
        "[1] Atemwegserkrankung"
      ],
      "frequencies": [
        0,
        0,
        0,
        0,
        435,
        0,
        19
      ]
    },
    "scale": "cat",
    "label_de": "Todesursache Atemwegserkrankung",
    "study": "soep-core",
    "statistics": {
      "valid": 19,
      "invalid": 435
    }
  },
  {
    "name": "bfvp1008",
    "dataset": "bfvp",
    "label": "cause of death: accident",
    "categories": {
      "values": [
        -6,
        -5,
        -4,
        -3,
        -2,
        -1,
        1
      ],
      "labels": [
        "[-6] Version of questionnaire with modified filtering",
        "[-5] Not included in this version of the questionnaire",
        "[-4] Inadmissible multiple response",
        "[-3] Answer improbable",
        "[-2] Does not apply",
        "[-1] No Answer",
        "[1] accident"
      ],
      "labels_de": [
        "[-6] Fragebogenversion mit geaenderter Filterfuehrung",
        "[-5] In Fragebogenversion nicht enthalten",
        "[-4] Unzulaessige Mehrfachantwort",
        "[-3] nicht valide",
        "[-2] trifft nicht zu",
        "[-1] keine Angabe",
        "[1] Unfall"
      ],
      "frequencies": [
        0,
        0,
        0,
        0,
        446,
        0,
        8
      ]
    },
    "scale": "cat",
    "label_de": "Todesursache Unfall",
    "study": "soep-core",
    "statistics": {
      "valid": 8,
      "invalid": 446
    }
  },
  {
    "name": "bfvp1009",
    "dataset": "bfvp",
    "label": "cause of death: other",
    "categories": {
      "values": [
        -6,
        -5,
        -4,
        -3,
        -2,
        -1,
        1
      ],
      "labels": [
        "[-6] Version of questionnaire with modified filtering",
        "[-5] Not included in this version of the questionnaire",
        "[-4] Inadmissible multiple response",
        "[-3] Answer improbable",
        "[-2] Does not apply",
        "[-1] No Answer",
        "[1] other cause"
      ],
      "labels_de": [
        "[-6] Fragebogenversion mit geaenderter Filterfuehrung",
        "[-5] In Fragebogenversion nicht enthalten",
        "[-4] Unzulaessige Mehrfachantwort",
        "[-3] nicht valide",
        "[-2] trifft nicht zu",
        "[-1] keine Angabe",
        "[1] Sonstige Ursache"
      ],
      "frequencies": [
        0,
        0,
        0,
        0,
        328,
        0,
        126
      ]
    },
    "scale": "cat",
    "label_de": "Todesursache sonstige Ursache",
    "study": "soep-core",
    "statistics": {
      "valid": 126,
      "invalid": 328
    }
  },
  {
    "name": "bfvp1010",
    "dataset": "bfvp",
    "label": "cause of death unknown",
    "categories": {
      "values": [
        -6,
        -5,
        -4,
        -3,
        -2,
        -1,
        1
      ],
      "labels": [
        "[-6] Version of questionnaire with modified filtering",
        "[-5] Not included in this version of the questionnaire",
        "[-4] Inadmissible multiple response",
        "[-3] Answer improbable",
        "[-2] Does not apply",
        "[-1] No Answer",
        "[1] Do Not Know"
      ],
      "labels_de": [
        "[-6] Fragebogenversion mit geaenderter Filterfuehrung",
        "[-5] In Fragebogenversion nicht enthalten",
        "[-4] Unzulaessige Mehrfachantwort",
        "[-3] nicht valide",
        "[-2] trifft nicht zu",
        "[-1] keine Angabe",
        "[1] Weiss nicht"
      ],
      "frequencies": [
        0,
        0,
        0,
        0,
        433,
        4,
        17
      ]
    },
    "scale": "cat",
    "label_de": "Todesursache unbekannt",
    "study": "soep-core",
    "statistics": {
      "valid": 17,
      "invalid": 437
    }
  },
  {
    "name": "bfvp1101",
    "dataset": "bfvp",
    "label": "left last will",
    "categories": {
      "values": [
        -6,
        -5,
        -4,
        -3,
        -2,
        -1,
        1,
        2,
        3
      ],
      "labels": [
        "[-6] Version of questionnaire with modified filtering",
        "[-5] Not included in this version of the questionnaire",
        "[-4] Inadmissible multiple response",
        "[-3] Answer improbable",
        "[-2] Does not apply",
        "[-1] No Answer",
        "[1] Yes",
        "[2] No",
        "[3] Do Not Know"
      ],
      "labels_de": [
        "[-6] Fragebogenversion mit geaenderter Filterfuehrung",
        "[-5] In Fragebogenversion nicht enthalten",
        "[-4] Unzulaessige Mehrfachantwort",
        "[-3] nicht valide",
        "[-2] trifft nicht zu",
        "[-1] keine Angabe",
        "[1] Ja",
        "[2] Nein",
        "[3] Weiss nicht"
      ],
      "frequencies": [
        0,
        0,
        0,
        0,
        0,
        8,
        144,
        285,
        17
      ]
    },
    "scale": "cat",
    "label_de": "Hinterlegung von Testament",
    "study": "soep-core",
    "statistics": {
      "valid": 446,
      "invalid": 8
    }
  },
  {
    "name": "bfvp1102",
    "dataset": "bfvp",
    "label": "left living will",
    "categories": {
      "values": [
        -6,
        -5,
        -4,
        -3,
        -2,
        -1,
        1,
        2,
        3
      ],
      "labels": [
        "[-6] Version of questionnaire with modified filtering",
        "[-5] Not included in this version of the questionnaire",
        "[-4] Inadmissible multiple response",
        "[-3] Answer improbable",
        "[-2] Does not apply",
        "[-1] No Answer",
        "[1] Yes",
        "[2] No",
        "[3] Do Not Know"
      ],
      "labels_de": [
        "[-6] Fragebogenversion mit geaenderter Filterfuehrung",
        "[-5] In Fragebogenversion nicht enthalten",
        "[-4] Unzulaessige Mehrfachantwort",
        "[-3] nicht valide",
        "[-2] trifft nicht zu",
        "[-1] keine Angabe",
        "[1] Ja",
        "[2] Nein",
        "[3] Weiss nicht"
      ],
      "frequencies": [
        0,
        0,
        0,
        0,
        0,
        8,
        193,
        234,
        19
      ]
    },
    "scale": "cat",
    "label_de": "Hinterlegung von Patientenverfuegung",
    "study": "soep-core",
    "statistics": {
      "valid": 446,
      "invalid": 8
    }
  },
  {
    "name": "bfvp1103",
    "dataset": "bfvp",
    "label": "left provisional power or attorney",
    "categories": {
      "values": [
        -6,
        -5,
        -4,
        -3,
        -2,
        -1,
        1,
        2,
        3
      ],
      "labels": [
        "[-6] Version of questionnaire with modified filtering",
        "[-5] Not included in this version of the questionnaire",
        "[-4] Inadmissible multiple response",
        "[-3] Answer improbable",
        "[-2] Does not apply",
        "[-1] No Answer",
        "[1] Yes",
        "[2] No",
        "[3] Do Not Know"
      ],
      "labels_de": [
        "[-6] Fragebogenversion mit geaenderter Filterfuehrung",
        "[-5] In Fragebogenversion nicht enthalten",
        "[-4] Unzulaessige Mehrfachantwort",
        "[-3] nicht valide",
        "[-2] trifft nicht zu",
        "[-1] keine Angabe",
        "[1] Ja",
        "[2] Nein",
        "[3] Weiss nicht"
      ],
      "frequencies": [
        0,
        0,
        0,
        0,
        0,
        8,
        200,
        221,
        25
      ]
    },
    "scale": "cat",
    "label_de": "Hinterlegung von Vorsorgevollmacht",
    "study": "soep-core",
    "statistics": {
      "valid": 446,
      "invalid": 8
    }
  },
  {
    "name": "bfvp1104",
    "dataset": "bfvp",
    "label": "left living will with instructions on use of death-delaying procedures",
    "categories": {
      "values": [
        -6,
        -5,
        -4,
        -3,
        -2,
        -1,
        1,
        2,
        3
      ],
      "labels": [
        "[-6] Version of questionnaire with modified filtering",
        "[-5] Not included in this version of the questionnaire",
        "[-4] Inadmissible multiple response",
        "[-3] Answer improbable",
        "[-2] Does not apply",
        "[-1] No Answer",
        "[1] Yes",
        "[2] No",
        "[3] do not know"
      ],
      "labels_de": [
        "[-6] Fragebogenversion mit geaenderter Filterfuehrung",
        "[-5] In Fragebogenversion nicht enthalten",
        "[-4] Unzulaessige Mehrfachantwort",
        "[-3] nicht valide",
        "[-2] trifft nicht zu",
        "[-1] keine Angabe",
        "[1] Ja",
        "[2] Nein",
        "[3] Weiss nciht"
      ],
      "frequencies": [
        0,
        0,
        0,
        0,
        0,
        9,
        107,
        315,
        23
      ]
    },
    "scale": "cat",
    "label_de": "Hinterlegung von Sterbeverfuegung",
    "study": "soep-core",
    "statistics": {
      "valid": 445,
      "invalid": 9
    }
  },
  {
    "name": "bfvp12",
    "dataset": "bfvp",
    "label": "limited mental capacity",
    "categories": {
      "values": [
        -6,
        -5,
        -4,
        -3,
        -2,
        -1,
        1,
        2,
        3
      ],
      "labels": [
        "[-6] Version of questionnaire with modified filtering",
        "[-5] Not included in this version of the questionnaire",
        "[-4] Inadmissible multiple response",
        "[-3] Answer improbable",
        "[-2] Does not apply",
        "[-1] No Answer",
        "[1] Yes",
        "[2] No",
        "[3] Do Not Know"
      ],
      "labels_de": [
        "[-6] Fragebogenversion mit geaenderter Filterfuehrung",
        "[-5] In Fragebogenversion nicht enthalten",
        "[-4] Unzulaessige Mehrfachantwort",
        "[-3] nicht valide",
        "[-2] trifft nicht zu",
        "[-1] keine Angabe",
        "[1] Ja",
        "[2] Nein",
        "[3] Weiss nicht"
      ],
      "frequencies": [
        0,
        0,
        0,
        0,
        0,
        2,
        113,
        333,
        6
      ]
    },
    "scale": "cat",
    "label_de": "Eingeschrkt. geistige Leistungsfaehigkeit bei V",
    "study": "soep-core",
    "statistics": {
      "valid": 452,
      "invalid": 2
    }
  },
  {
    "name": "bfvp13",
    "dataset": "bfvp",
    "label": "health status 3 month before death",
    "categories": {
      "values": [
        -6,
        -5,
        -4,
        -3,
        -2,
        -1,
        1,
        2,
        3,
        4,
        5
      ],
      "labels": [
        "[-6] Version of questionnaire with modified filtering",
        "[-5] Not included in this version of the questionnaire",
        "[-4] Inadmissible multiple response",
        "[-3] Answer improbable",
        "[-2] Does not apply",
        "[-1] No Answer",
        "[1] Very Good",
        "[2] Good",
        "[3] Satisfactory",
        "[4] Poor",
        "[5] Bad"
      ],
      "labels_de": [
        "[-6] Fragebogenversion mit geaenderter Filterfuehrung",
        "[-5] In Fragebogenversion nicht enthalten",
        "[-4] Unzulaessige Mehrfachantwort",
        "[-3] nicht valide",
        "[-2] trifft nicht zu",
        "[-1] keine Angabe",
        "[1] Sehr gut",
        "[2] Gut",
        "[3] Zufriedenstellend",
        "[4] Weniger gut",
        "[5] Schlecht"
      ],
      "frequencies": [
        0,
        0,
        0,
        0,
        0,
        6,
        12,
        49,
        64,
        104,
        219
      ]
    },
    "scale": "cat",
    "label_de": "Gesundheitszustand der/des V 3 Monate vor Tod",
    "study": "soep-core",
    "statistics": {
      "valid": 448,
      "invalid": 6
    }
  },
  {
    "name": "bfvp15",
    "dataset": "bfvp",
    "label": "deceased was in need of care three months before death",
    "categories": {
      "values": [
        -6,
        -5,
        -4,
        -3,
        -2,
        -1,
        1,
        2
      ],
      "labels": [
        "[-6] Version of questionnaire with modified filtering",
        "[-5] Not included in this version of the questionnaire",
        "[-4] Inadmissible multiple response",
        "[-3] Answer improbable",
        "[-2] Does not apply",
        "[-1] No Answer",
        "[1] Yes",
        "[2] No"
      ],
      "labels_de": [
        "[-6] Fragebogenversion mit geaenderter Filterfuehrung",
        "[-5] In Fragebogenversion nicht enthalten",
        "[-4] Unzulaessige Mehrfachantwort",
        "[-3] nicht valide",
        "[-2] trifft nicht zu",
        "[-1] keine Angabe",
        "[1] Ja",
        "[2] Nein"
      ],
      "frequencies": [
        0,
        0,
        0,
        0,
        0,
        4,
        278,
        172
      ]
    },
    "scale": "cat",
    "label_de": "V 3 Monate vor Tod hilfe-,pflegebeduerftig",
    "study": "soep-core",
    "statistics": {
      "valid": 450,
      "invalid": 4
    }
  },
  {
    "name": "bfvp1501",
    "dataset": "bfvp",
    "label": "help with errands",
    "categories": {
      "values": [
        -6,
        -5,
        -4,
        -3,
        -2,
        -1,
        1
      ],
      "labels": [
        "[-6] Version of questionnaire with modified filtering",
        "[-5] Not included in this version of the questionnaire",
        "[-4] Inadmissible multiple response",
        "[-3] Answer improbable",
        "[-2] Does not apply",
        "[-1] No Answer",
        "[1] Yes"
      ],
      "labels_de": [
        "[-6] Fragebogenversion mit geaenderter Filterfuehrung",
        "[-5] In Fragebogenversion nicht enthalten",
        "[-4] Unzulaessige Mehrfachantwort",
        "[-3] nicht valide",
        "[-2] trifft nicht zu",
        "[-1] keine Angabe",
        "[1] Ja"
      ],
      "frequencies": [
        0,
        0,
        0,
        0,
        217,
        0,
        237
      ]
    },
    "scale": "cat",
    "label_de": "Hilfe bei Besorgg./Erledigg. ausser Haus",
    "study": "soep-core",
    "statistics": {
      "valid": 237,
      "invalid": 217
    }
  },
  {
    "name": "bfvp1502",
    "dataset": "bfvp",
    "label": "help in household with eating/drinking",
    "categories": {
      "values": [
        -6,
        -5,
        -4,
        -3,
        -2,
        -1,
        1
      ],
      "labels": [
        "[-6] Version of questionnaire with modified filtering",
        "[-5] Not included in this version of the questionnaire",
        "[-4] Inadmissible multiple response",
        "[-3] Answer improbable",
        "[-2] Does not apply",
        "[-1] No Answer",
        "[1] Yes"
      ],
      "labels_de": [
        "[-6] Fragebogenversion mit geaenderter Filterfuehrung",
        "[-5] In Fragebogenversion nicht enthalten",
        "[-4] Unzulaessige Mehrfachantwort",
        "[-3] nicht valide",
        "[-2] trifft nicht zu",
        "[-1] keine Angabe",
        "[1] Ja"
      ],
      "frequencies": [
        0,
        0,
        0,
        0,
        226,
        0,
        228
      ]
    },
    "scale": "cat",
    "label_de": "Hilfe im HH, bei Zunahme Mahlzeiten/Trinken",
    "study": "soep-core",
    "statistics": {
      "valid": 228,
      "invalid": 226
    }
  },
  {
    "name": "bfvp1503",
    "dataset": "bfvp",
    "label": "help with simple personal care: dressing, bathing...",
    "categories": {
      "values": [
        -6,
        -5,
        -4,
        -3,
        -2,
        -1,
        1
      ],
      "labels": [
        "[-6] Version of questionnaire with modified filtering",
        "[-5] Not included in this version of the questionnaire",
        "[-4] Inadmissible multiple response",
        "[-3] Answer improbable",
        "[-2] Does not apply",
        "[-1] No Answer",
        "[1] Yes"
      ],
      "labels_de": [
        "[-6] Fragebogenversion mit geaenderter Filterfuehrung",
        "[-5] In Fragebogenversion nicht enthalten",
        "[-4] Unzulaessige Mehrfachantwort",
        "[-3] nicht valide",
        "[-2] trifft nicht zu",
        "[-1] keine Angabe",
        "[1] Ja"
      ],
      "frequencies": [
        0,
        0,
        0,
        0,
        232,
        0,
        222
      ]
    },
    "scale": "cat",
    "label_de": "Hilfe bei einfacher Pflege: kleiden, waschen...",
    "study": "soep-core",
    "statistics": {
      "valid": 222,
      "invalid": 232
    }
  },
  {
    "name": "bfvp1504",
    "dataset": "bfvp",
    "label": "help in getting in and out of bed, using toilet",
    "categories": {
      "values": [
        -6,
        -5,
        -4,
        -3,
        -2,
        -1,
        1
      ],
      "labels": [
        "[-6] Version of questionnaire with modified filtering",
        "[-5] Not included in this version of the questionnaire",
        "[-4] Inadmissible multiple response",
        "[-3] Answer improbable",
        "[-2] Does not apply",
        "[-1] No Answer",
        "[1] Yes"
      ],
      "labels_de": [
        "[-6] Fragebogenversion mit geaenderter Filterfuehrung",
        "[-5] In Fragebogenversion nicht enthalten",
        "[-4] Unzulaessige Mehrfachantwort",
        "[-3] nicht valide",
        "[-2] trifft nicht zu",
        "[-1] keine Angabe",
        "[1] Ja"
      ],
      "frequencies": [
        0,
        0,
        0,
        0,
        273,
        0,
        181
      ]
    },
    "scale": "cat",
    "label_de": "Hilfe bei Umbetten, Stuhlgang",
    "study": "soep-core",
    "statistics": {
      "valid": 181,
      "invalid": 273
    }
  },
  {
    "name": "bfvp1601",
    "dataset": "bfvp",
    "label": "satisfaction of deceased 1 year before death",
    "categories": {
      "values": [
        -6,
        -5,
        -4,
        -3,
        -2,
        -1,
        0,
        1,
        2,
        3,
        4,
        5,
        6,
        7,
        8,
        9,
        10
      ],
      "labels": [
        "[-6] Version of questionnaire with modified filtering",
        "[-5] Not included in this version of the questionnaire",
        "[-4] Inadmissible multiple response",
        "[-3] Answer improbable",
        "[-2] Does not apply",
        "[-1] No Answer",
        "[0] 0 Satisfied: On Scale 0-Low to 10-High",
        "[1] 1 Satisfied: On Scale 0-Low to 10-High",
        "[2] 2 Satisfied: On Scale 0-Low to 10-High",
        "[3] 3 Satisfied: On Scale 0-Low to 10-High",
        "[4] 4 Satisfied: On Scale 0-Low to 10-High",
        "[5] 5 Satisfied: On Scale 0-Low to 10-High",
        "[6] 6 Satisfied: On Scale 0-Low to 10-High",
        "[7] 7 Satisfied: On Scale 0-Low to 10-High",
        "[8] 8 Satisfied: On Scale 0-Low to 10-High",
        "[9] 9 Satisfied: On Scale 0-Low to 10-High",
        "[10] 10 Satisfied: On Scale 0-Low to 10-High"
      ],
      "labels_de": [
        "[-6] Fragebogenversion mit geaenderter Filterfuehrung",
        "[-5] In Fragebogenversion nicht enthalten",
        "[-4] Unzulaessige Mehrfachantwort",
        "[-3] nicht valide",
        "[-2] trifft nicht zu",
        "[-1] keine Angabe",
        "[0] 0 Zufrieden: Skala 0-Niedrig bis 10-Hoch",
        "[1] 1 Zufrieden: Skala 0-Niedrig bis 10-Hoch",
        "[2] 2 Zufrieden: Skala 0-Niedrig bis 10-Hoch",
        "[3] 3 Zufrieden: Skala 0-Niedrig bis 10-Hoch",
        "[4] 4 Zufrieden: Skala 0-Niedrig bis 10-Hoch",
        "[5] 5 Zufrieden: Skala 0-Niedrig bis 10-Hoch",
        "[6] 6 Zufrieden: Skala 0-Niedrig bis 10-Hoch",
        "[7] 7 Zufrieden: Skala 0-Niedrig bis 10-Hoch",
        "[8] 8 Zufrieden: Skala 0-Niedrig bis 10-Hoch",
        "[9] 9 Zufrieden: Skala 0-Niedrig bis 10-Hoch",
        "[10] 10 Zufrieden: Skala 0-Niedrig bis 10-Hoch"
      ],
      "frequencies": [
        0,
        0,
        0,
        0,
        0,
        41,
        0,
        17,
        28,
        31,
        25,
        57,
        47,
        57,
        97,
        32,
        22
      ]
    },
    "scale": "cat",
    "label_de": "Zufriedenheit der/des V 1 Jahr vor Tod",
    "study": "soep-core",
    "statistics": {
      "valid": 413,
      "invalid": 41
    }
  },
  {
    "name": "bfvp1505",
    "dataset": "bfvp",
    "label": "help in total, n.a.",
    "categories": {
      "values": [
        -6,
        -5,
        -4,
        -3,
        -2,
        -1,
        1
      ],
      "labels": [
        "[-6] Version of questionnaire with modified filtering",
        "[-5] Not included in this version of the questionnaire",
        "[-4] Inadmissible multiple response",
        "[-3] Answer improbable",
        "[-2] Does not apply",
        "[-1] No Answer",
        "[1] Yes"
      ],
      "labels_de": [
        "[-6] Fragebogenversion mit geaenderter Filterfuehrung",
        "[-5] In Fragebogenversion nicht enthalten",
        "[-4] Unzulaessige Mehrfachantwort",
        "[-3] nicht valide",
        "[-2] trifft nicht zu",
        "[-1] keine Angabe",
        "[1] Ja"
      ],
      "frequencies": [
        0,
        0,
        0,
        0,
        452,
        2,
        0
      ]
    },
    "scale": "cat",
    "label_de": "Hilfe Gesamt k.A.",
    "study": "soep-core",
    "statistics": {
      "valid": 0,
      "invalid": 454
    }
  },
  {
    "name": "bfvp1602",
    "dataset": "bfvp",
    "label": "satisfaction of deceased 3 months before death",
    "categories": {
      "values": [
        -6,
        -5,
        -4,
        -3,
        -2,
        -1,
        0,
        1,
        2,
        3,
        4,
        5,
        6,
        7,
        8,
        9,
        10
      ],
      "labels": [
        "[-6] Version of questionnaire with modified filtering",
        "[-5] Not included in this version of the questionnaire",
        "[-4] Inadmissible multiple response",
        "[-3] Answer improbable",
        "[-2] Does not apply",
        "[-1] No Answer",
        "[0] 0 Satisfied: On Scale 0-Low to 10-High",
        "[1] 1 Satisfied: On Scale 0-Low to 10-High",
        "[2] 2 Satisfied: On Scale 0-Low to 10-High",
        "[3] 3 Satisfied: On Scale 0-Low to 10-High",
        "[4] 4 Satisfied: On Scale 0-Low to 10-High",
        "[5] 5 Satisfied: On Scale 0-Low to 10-High",
        "[6] 6 Satisfied: On Scale 0-Low to 10-High",
        "[7] 7 Satisfied: On Scale 0-Low to 10-High",
        "[8] 8 Satisfied: On Scale 0-Low to 10-High",
        "[9] 9 Satisfied: On Scale 0-Low to 10-High",
        "[10] 10 Satisfied: On Scale 0-Low to 10-High"
      ],
      "labels_de": [
        "[-6] Fragebogenversion mit geaenderter Filterfuehrung",
        "[-5] In Fragebogenversion nicht enthalten",
        "[-4] Unzulaessige Mehrfachantwort",
        "[-3] nicht valide",
        "[-2] trifft nicht zu",
        "[-1] keine Angabe",
        "[0] 0 Zufrieden: Skala 0-Niedrig bis 10-Hoch",
        "[1] 1 Zufrieden: Skala 0-Niedrig bis 10-Hoch",
        "[2] 2 Zufrieden: Skala 0-Niedrig bis 10-Hoch",
        "[3] 3 Zufrieden: Skala 0-Niedrig bis 10-Hoch",
        "[4] 4 Zufrieden: Skala 0-Niedrig bis 10-Hoch",
        "[5] 5 Zufrieden: Skala 0-Niedrig bis 10-Hoch",
        "[6] 6 Zufrieden: Skala 0-Niedrig bis 10-Hoch",
        "[7] 7 Zufrieden: Skala 0-Niedrig bis 10-Hoch",
        "[8] 8 Zufrieden: Skala 0-Niedrig bis 10-Hoch",
        "[9] 9 Zufrieden: Skala 0-Niedrig bis 10-Hoch",
        "[10] 10 Zufrieden: Skala 0-Niedrig bis 10-Hoch"
      ],
      "frequencies": [
        0,
        0,
        0,
        0,
        0,
        82,
        0,
        43,
        52,
        52,
        30,
        44,
        28,
        27,
        62,
        22,
        12
      ]
    },
    "scale": "cat",
    "label_de": "Zufriedenheit der/des V 3 Monate vor Tod",
    "study": "soep-core",
    "statistics": {
      "valid": 372,
      "invalid": 82
    }
  },
  {
    "name": "bfvform",
    "dataset": "bfvp",
    "label": "survey instrument",
    "categories": {
      "values": [
        -6,
        -5,
        -4,
        -3,
        -2,
        -1,
        0,
        1,
        2,
        3,
        4,
        5,
        8,
        9,
        10
      ],
      "labels": [
        "[-6] Version of questionnaire with modified filtering",
        "[-5] Not included in this version of the questionnaire",
        "[-4] Inadmissible multiple response",
        "[-3] Answer improbable",
        "[-2] Does not apply",
        "[-1] No Answer",
        "[0] By Telephone",
        "[1] Oral Interview",
        "[2] Written Ques. Interviewer",
        "[3] Written Ques. No Interviewer",
        "[4] Oral And Written",
        "[5] Proxy",
        "[8] Written, By Mail",
        "[9] CAPI",
        "[10] CAWI"
      ],
      "labels_de": [
        "[-6] Fragebogenversion mit geaenderter Filterfuehrung",
        "[-5] In Fragebogenversion nicht enthalten",
        "[-4] Unzulaessige Mehrfachantwort",
        "[-3] nicht valide",
        "[-2] trifft nicht zu",
        "[-1] keine Angabe",
        "[0] Telefonisch",
        "[1] Muendl.Interview",
        "[2] Ausgef.m.Interviewer",
        "[3] Ausgef.o.Interviewer",
        "[4] Teils muendl.,schr.",
        "[5] Proxy",
        "[8] Schriftlich",
        "[9] CAPI",
        "[10] CAWI"
      ],
      "frequencies": [
        0,
        0,
        0,
        0,
        0,
        24,
        0,
        32,
        6,
        41,
        0,
        0,
        6,
        310,
        35
      ]
    },
    "scale": "cat",
    "label_de": "Befragungsart/Befragungsdurchfuehrung",
    "study": "soep-core",
    "statistics": {
      "valid": 430,
      "invalid": 24
    }
  },
  {
    "name": "bfvp17",
    "dataset": "bfvp",
    "label": "change in personal life since death",
    "categories": {
      "values": [
        -6,
        -5,
        -4,
        -3,
        -2,
        -1,
        1,
        2,
        3
      ],
      "labels": [
        "[-6] Version of questionnaire with modified filtering",
        "[-5] Not included in this version of the questionnaire",
        "[-4] Inadmissible multiple response",
        "[-3] Answer improbable",
        "[-2] Does not apply",
        "[-1] No Answer",
        "[1] I have to order my life in a new way",
        "[2] some things change now",
        "[3] nothing will change because of that"
      ],
      "labels_de": [
        "[-6] Fragebogenversion mit geaenderter Filterfuehrung",
        "[-5] In Fragebogenversion nicht enthalten",
        "[-4] Unzulaessige Mehrfachantwort",
        "[-3] nicht valide",
        "[-2] trifft nicht zu",
        "[-1] keine Angabe",
        "[1] Ich muss mein Leben ganz neu ordnen",
        "[2] Einige Dinge aendern sich nun",
        "[3] Dadurch aendert sich eher nichts"
      ],
      "frequencies": [
        0,
        0,
        0,
        0,
        0,
        3,
        85,
        205,
        161
      ]
    },
    "scale": "cat",
    "label_de": "Veraenderung des pers. Lebens seit Tod",
    "study": "soep-core",
    "statistics": {
      "valid": 451,
      "invalid": 3
    }
  },
  {
    "name": "bfvdatt",
    "dataset": "bfvp",
    "label": "day of interview",
    "categories": {
      "values": [],
      "labels": []
    },
    "scale": "number",
    "label_de": "Interviewtag",
    "study": "soep-core",
    "statistics": {
      "Min.": 1.0,
      "1st Qu.": 10.0,
      "Median": 17.5,
      "Mean": 16.610132158590307,
      "3rd Qu.": 23.0,
      "Max.": 31.0,
      "valid": 454,
      "invalid": 0
    }
  },
  {
    "name": "bfvdatm",
    "dataset": "bfvp",
    "label": "month of interview",
    "categories": {
      "values": [
        -6,
        -5,
        -4,
        -3,
        -2,
        -1,
        1,
        2,
        3,
        4,
        5,
        6,
        7,
        8,
        9,
        10,
        11,
        12
      ],
      "labels": [
        "[-6] Version of questionnaire with modified filtering",
        "[-5] Not included in this version of the questionnaire",
        "[-4] Inadmissible multiple response",
        "[-3] Answer improbable",
        "[-2] Does not apply",
        "[-1] No Answer",
        "[1] January",
        "[2] February",
        "[3] March",
        "[4] April",
        "[5] May",
        "[6] June",
        "[7] July",
        "[8] August",
        "[9] September",
        "[10] October",
        "[11] November",
        "[12] December"
      ],
      "labels_de": [
        "[-6] Fragebogenversion mit geaenderter Filterfuehrung",
        "[-5] In Fragebogenversion nicht enthalten",
        "[-4] Unzulaessige Mehrfachantwort",
        "[-3] nicht valide",
        "[-2] trifft nicht zu",
        "[-1] keine Angabe",
        "[1] Januar",
        "[2] Februar",
        "[3] Maerz",
        "[4] April",
        "[5] Mai",
        "[6] Juni",
        "[7] Juli",
        "[8] August",
        "[9] September",
        "[10] Oktober",
        "[11] November",
        "[12] Dezember"
      ],
      "frequencies": [
        0,
        0,
        0,
        0,
        0,
        0,
        0,
        97,
        107,
        71,
        44,
        41,
        32,
        26,
        21,
        13,
        2,
        0
      ]
    },
    "scale": "cat",
    "label_de": "Interviewmonat",
    "study": "soep-core",
    "statistics": {
      "valid": 454,
      "invalid": 0
    }
  },
  {
    "name": "bfvdatst",
    "dataset": "bfvp",
    "label": "End of Interview (Hour)",
    "categories": {
      "values": [],
      "labels": []
    },
    "scale": "number",
    "label_de": "Interview beendet Uhrzeit (Stunde)",
    "study": "soep-core",
    "statistics": {
      "Min.": 5.0,
      "1st Qu.": 12.0,
      "Median": 16.0,
      "Mean": 15.194630872483222,
      "3rd Qu.": 18.0,
      "Max.": 22.0,
      "valid": 447,
      "invalid": 7
    }
  },
  {
    "name": "bfvdatmi",
    "dataset": "bfvp",
    "label": "End of Interview (Minutes)",
    "categories": {
      "values": [],
      "labels": []
    },
    "scale": "number",
    "label_de": "Interview beendet Uhrzeit (Minuten)",
    "study": "soep-core",
    "statistics": {
      "Min.": 1.0,
      "1st Qu.": 15.0,
      "Median": 30.0,
      "Mean": 29.197590361445783,
      "3rd Qu.": 44.5,
      "Max.": 59.0,
      "valid": 415,
      "invalid": 39
    }
  },
  {
    "name": "intid",
    "dataset": "bfvp",
    "label": "Interviewer ID",
    "categories": {
      "values": [],
      "labels": []
    },
    "scale": "number",
    "label_de": "Interviewer ID",
    "study": "soep-core",
    "statistics": {
      "Min.": 1001013.0,
      "1st Qu.": 1002060.0,
      "Median": 1003207.0,
      "Mean": 1003186.5472154964,
      "3rd Qu.": 1004342.0,
      "Max.": 1005396.0,
      "valid": 413,
      "invalid": 41
    }
  },
  {
    "name": "vpid",
    "dataset": "bfvp",
    "label": "Unchanging ID Person deceased",
    "categories": {
      "values": [],
      "labels": []
    },
    "scale": "number",
    "label_de": "Unveraenderliche Personennr. des Verstorbenen",
    "study": "soep-core",
    "statistics": {
      "Min.": 33001.0,
      "1st Qu.": 2900574.75,
      "Median": 20163799.0,
      "Mean": 16376261.682819383,
      "3rd Qu.": 30648875.5,
      "Max.": 33429099.0,
      "valid": 454,
      "invalid": 0
    }
  }
]